libname/__init__.py
libname/hello.py
Wpip-0.0.1.dist-info/METADATA
Wpip-0.0.1.dist-info/WHEEL
Wpip-0.0.1.dist-info/top_level.txt
Wpip-0.0.1.dist-info/RECORD
