Metadata-Version: 2.1
Name: Wpip
Version: 0.0.1
Summary: TestPiP By WALKER
Home-page: UNKNOWN
Author: W4lk3r
Author-email: <w000alker@gmail.com>
License: UNKNOWN
Keywords: requests
Platform: UNKNOWN
Classifier: Development Status :: 1 - Planning
Classifier: Intended Audience :: Developers
Classifier: Programming Language :: Python :: 3
Classifier: Operating System :: Unix
Classifier: Operating System :: MacOS :: MacOS X
Classifier: Operating System :: Microsoft :: Windows
Requires-Dist: requests
